tansive/skillset_sdk/__init__.py
tansive/skillset_sdk/client.py
tansive/skillset_sdk/exceptions.py
tansive_skillset_sdk-0.1.0a2.dist-info/licenses/LICENSE
tansive_skillset_sdk-0.1.0a2.dist-info/METADATA
tansive_skillset_sdk-0.1.0a2.dist-info/WHEEL
tansive_skillset_sdk-0.1.0a2.dist-info/top_level.txt
tansive_skillset_sdk-0.1.0a2.dist-info/RECORD
