Metadata-Version: 2.4
Name: tansive-skillset-sdk
Version: 0.1.0a2
Summary: Tansive SkillSet SDK
Author-email: "Tansive, Inc." <support@tansive.com>
License: MIT
Project-URL: Homepage, https://github.com/tansive/skillset-sdk-python
Project-URL: Bug Reports, https://github.com/tansive/skillset-sdk-python/issues
Project-URL: Source, https://github.com/tansive/skillset-sdk-python
Keywords: automation,sdk,agents,tansive
Classifier: Development Status :: 3 - Alpha
Classifier: Intended Audience :: Developers
Classifier: License :: OSI Approved :: MIT License
Classifier: Operating System :: OS Independent
Classifier: Programming Language :: Python :: 3
Classifier: Programming Language :: Python :: 3.7
Classifier: Programming Language :: Python :: 3.8
Classifier: Programming Language :: Python :: 3.9
Classifier: Programming Language :: Python :: 3.10
Classifier: Programming Language :: Python :: 3.11
Requires-Python: >=3.7
License-File: LICENSE
Requires-Dist: requests>=2.25.0
Dynamic: license-file
